yandex_neurosupport/__init__.py
yandex_neurosupport/client.py
yandex_neurosupport/example.py
yandex_neurosupport/exceptions.py
yandex_neurosupport/utils.py
yandex_neurosupport-0.1.0.dist-info/licenses/AUTHORS
yandex_neurosupport-0.1.0.dist-info/licenses/LICENSE
yandex_neurosupport-0.1.0.dist-info/licenses/NOTICES
yandex_neurosupport-0.1.0.dist-info/METADATA
yandex_neurosupport-0.1.0.dist-info/WHEEL
yandex_neurosupport-0.1.0.dist-info/top_level.txt
yandex_neurosupport-0.1.0.dist-info/RECORD
