Metadata-Version: 2.4
Name: yandex_neurosupport
Version: 0.1.0
Summary: Клиент для Yandex NeuroSupport API: обертка для индексации документов и генеративных ответов
Home-page: https://github.com/yandex/neurosupport-api
Author: Timur Sukharev
Author-email: tsukharev@yandex-team.ru
License: Apache-2.0
Keywords: yandex api neurosupport client supportgpt
Classifier: Programming Language :: Python :: 3.8
Classifier: Programming Language :: Python :: 3.9
Classifier: Programming Language :: Python :: 3.10
Classifier: License :: OSI Approved :: Apache Software License
Classifier: Operating System :: OS Independent
Classifier: Topic :: Software Development :: Libraries :: Python Modules
Requires-Python: >=3.8
License-File: LICENSE
License-File: NOTICES
License-File: AUTHORS
Requires-Dist: requests>=2.25.0
Dynamic: author
Dynamic: author-email
Dynamic: classifier
Dynamic: description
Dynamic: description-content-type
Dynamic: home-page
Dynamic: keywords
Dynamic: license
Dynamic: license-file
Dynamic: requires-dist
Dynamic: requires-python
Dynamic: summary
